MANIFEST.in
README.md
setup.py
scriptedforms/.yarnrc
scriptedforms/Apache-2.0
scriptedforms/LICENSE
scriptedforms/__init__.py
scriptedforms/__main__.py
scriptedforms/_scriptedforms_handlers.py
scriptedforms/_utilities.py
scriptedforms/_version.py
scriptedforms/angular.json
scriptedforms/index.html
scriptedforms/package.json
scriptedforms/scriptedforms.json
scriptedforms/scriptedforms.py
scriptedforms/simonbiggs-scriptedforms-v0.10.1.tgz
scriptedforms/tsconfig.json
scriptedforms/tslint.json
scriptedforms/webpack.config.js
scriptedforms/webpack.dev.js
scriptedforms/webpack.prod.js
scriptedforms/yarn.lock
scriptedforms.egg-info/PKG-INFO
scriptedforms.egg-info/SOURCES.txt
scriptedforms.egg-info/dependency_links.txt
scriptedforms.egg-info/entry_points.txt
scriptedforms.egg-info/requires.txt
scriptedforms.egg-info/top_level.txt
scriptedforms/dev_utilities/__init__.py
scriptedforms/dev_utilities/jupyterlab_extracts/LICENSE
scriptedforms/dev_utilities/jupyterlab_extracts/__init__.py
scriptedforms/dev_utilities/jupyterlab_extracts/process.py
scriptedforms/docs/create-your-own-angular-jupyterlab-extension.md
scriptedforms/docs/docs-base.md
scriptedforms/docs/docs.css
scriptedforms/docs/landing-page.md
scriptedforms/e2e/package.json
scriptedforms/e2e/run-test.py
scriptedforms/e2e/tsconfig.e2e.json
scriptedforms/e2e/tsconfig.json
scriptedforms/e2e/tslint.json
scriptedforms/e2e/yarn.lock
scriptedforms/e2e/src/.gitignore
scriptedforms/e2e/src/detailed.form.md
scriptedforms/e2e/src/landing-page.md
scriptedforms/e2e/src/landing-page.spec.ts
scriptedforms/e2e/src/protractor.conf.ts
scriptedforms/e2e/src/section-button.md
scriptedforms/e2e/src/section-button.spec.ts
scriptedforms/e2e/src/section-live.md
scriptedforms/e2e/src/section-live.spec.ts
scriptedforms/e2e/src/section-output.md
scriptedforms/e2e/src/section-output.spec.ts
scriptedforms/e2e/src/section-start.md
scriptedforms/e2e/src/section-start.spec.ts
scriptedforms/e2e/src/variable-string.md
scriptedforms/e2e/src/variable-string.spec.ts
scriptedforms/e2e/src/variable-table.csv
scriptedforms/e2e/src/variable-table.md
scriptedforms/e2e/src/variable-table.py
scriptedforms/e2e/src/variable-table.spec.ts
scriptedforms/e2e/src/watchdog-manage.md
