Metadata-Version: 1.2
Name: scriptedforms
Version: 0.10.1
Summary: ScriptedForms.
Home-page: https://scriptedforms.com.au
Author: Simon Biggs
Author-email: sbiggs@scriptedforms.com.au
License: AGPL-3.0+
Platform: UNKNOWN
Requires-Python: >=3.5
